ytdl_server/__init__.py
ytdl_server/celery.py
ytdl_server/config.py
ytdl_server/config_option.py
ytdl_server/custom_opt.py
ytdl_server/database.py
ytdl_server/db_util.py
ytdl_server/error.py
ytdl_server/error_base.py
ytdl_server/flask.py
ytdl_server/flask_config.py
ytdl_server/health.py
ytdl_server/http_error.py
ytdl_server/job.py
ytdl_server/json.py
ytdl_server/meta.py
ytdl_server/py.typed
ytdl_server/run_celery.py
ytdl_server/task.py
ytdl_server/type.py
ytdl_server/util.py
ytdl_server/version.py
ytdl_server/ytdl.py
ytdl_server-1.2.0.dist-info/licenses/COPYING
ytdl_server-1.2.0.dist-info/METADATA
ytdl_server-1.2.0.dist-info/WHEEL
ytdl_server-1.2.0.dist-info/top_level.txt
ytdl_server-1.2.0.dist-info/RECORD
