Metadata-Version: 2.4
Name: ytdl-server
Version: 1.2.0
Summary: Download videos to a remote server using youtube-dl via a REST API
Home-page: https://gitlab.com/adralioh/ytdl-server
Author: Adralioh
Project-URL: Documentation, https://adralioh.gitlab.io/ytdl-server
Keywords: youtube-dl,yt-dlp,youtube,download,rest,api
Classifier: Development Status :: 5 - Production/Stable
Classifier: Framework :: Celery
Classifier: Framework :: Flask
Classifier: Intended Audience :: System Administrators
Classifier: License :: OSI Approved :: GNU General Public License v3 (GPLv3)
Classifier: Programming Language :: Python :: 3
Classifier: Topic :: Multimedia :: Video
Classifier: Topic :: System :: Archiving
Classifier: Typing :: Typed
Requires-Python: >=3.9
License-File: COPYING
Requires-Dist: Flask<2.2
Requires-Dist: Flask-SQLAlchemy
Requires-Dist: Werkzeug<3
Requires-Dist: celery
Requires-Dist: billiard
Requires-Dist: SQLAlchemy<2
Requires-Dist: PyYAML
Provides-Extra: dbapi
Requires-Dist: psycopg2; extra == "dbapi"
Dynamic: license-file
